numpy/__init__.py
pythonx/__init__.py
pythonx-0.0.2.dist-info/METADATA
pythonx-0.0.2.dist-info/RECORD
pythonx-0.0.2.dist-info/WHEEL
pythonx-0.0.2.dist-info/top_level.txt
pyx/__init__.py
