Metadata-Version: 2.1
Name: pythonx
Version: 0.0.2
Summary: Python X
Home-page: https://github.com/jinsyin/x/tree/master/pythonx
Author: Jins Yin
Author-email: jinsyin@gmail.com
License: UNKNOWN
Platform: UNKNOWN
Classifier: Programming Language :: Python :: 3
Classifier: License :: OSI Approved :: MIT License
Classifier: Operating System :: OS Independent
